__temp_migrations/__init__.py
__temp_migrations/auth/0001_initial.py
__temp_migrations/auth/__init__.py
__temp_migrations/contenttypes/0001_initial.py
__temp_migrations/contenttypes/__init__.py
__temp_migrations/otree/0001_initial.py
__temp_migrations/otree/__init__.py
__temp_migrations/qvsr/0001_initial.py
__temp_migrations/qvsr/__init__.py
__temp_migrations/sessions/0001_initial.py
__temp_migrations/sessions/__init__.py
qvsr/__init__.py
qvsr/models.py
qvsr/pages.py
qvsr/_builtin/__init__.py
qvsr/templates/__init__.py
otree_qvsr-0.2.dist-info/METADATA
otree_qvsr-0.2.dist-info/WHEEL
otree_qvsr-0.2.dist-info/top_level.txt
otree_qvsr-0.2.dist-info/RECORD
