Metadata-Version: 2.1
Name: otree-qvsr
Version: 0.2
Summary: QVSR package
Author: Joseph Noblepal
Author-email: josephnoblepal@gmail.com
License: MIT
Keywords: python,qvsr,otree
Classifier: Programming Language :: Python :: 3
Classifier: Operating System :: MacOS :: MacOS X
Classifier: Operating System :: Microsoft :: Windows
Classifier: Operating System :: Unix
